[{
        "title": "కేసీఆర్‌ థర్డ్‌ ఫ్రంట్‌కు జనసేన మద్దతు",
		"content": "టీఆర్‌ఎస్‌ అధినేత, తెలంగాణ సీఎం కేసీఆర్‌ ఏర్పాటు చేయ బోయే థర్డ్‌ ఫ్రంట్‌కు జనసేన పూర్తి మద్దతు ఇస్తుందని ఆ పార్టీ అధినేత పవన్‌ కల్యాణ్‌ ప్రకటించారు. రాష్ట్రాల్లో చోటుచేసుకునే సున్నిత సమస్యలను అర్థం చేసుకునే కొందరు వ్యక్తుల సమూహం దేశ రాజకీయాల్లో అవసరం. రాజకీయాల్లోకి కొత్త రక్తం రావాలి. కొత్త ఆలోచన రావాలి. కొత్త రక్తంతో కూడిన థర్డ్‌ ఫ్రంట్‌ కావాలి. దీనికి అంకురార్పణ చేద్దామనుకున్న కేసీఆర్‌ నిర్ణయాన్ని స్వాగతిస్తున్నాను’ అని పవన్‌ అన్నారు. ",
		"img_url": "https://github.com/VattipalliSridhar/Telugu-Quotes-Wallpapers/raw/master/news/ap/PAWAN.jpg"
    },{
        "title": "నేటి నుంచి అసెంబ్లీ బడ్జెట్‌ సమావేశాలు: ఆంధ్రప్రదేశ్",
		"content": "రాష్ట్ర శాసనసభ బడ్జెట్‌ సమావేశాలు సోమవారం నుంచి ప్రారంభం కానున్నాయి. సమావేశాల్లో 2018–19 బడ్జెట్‌ను ఈ నెల 8న ప్రభుత్వం ప్రవేశపెట్టనుంది. సోమవారం ఉదయం 9.30కు ఉభయ సభలను ఉద్దేశించి గవర్నర్‌ ప్రసంగిస్తారు. అనంతరం సభ మంగళవారానికి వాయిదా పడనుంది. ఇవి 14వ అసెంబ్లీ 11వ సమావేశాలు కాగా, శాసన మండలికి 13వ సమావేశాలు. ఈ సమావేశాలకు ప్రతిపక్షం వైఎస్సార్‌సీపీ హాజరవుతుందా, లేదా అన్నది ఫిరాయింపు ఎమ్మెల్యేలపై స్పీకర్‌ చర్యలు తీసుకోవడంపై ఆధారపడి ఉంది. ",
		"img_url": "https://github.com/VattipalliSridhar/Telugu-Quotes-Wallpapers/raw/master/news/ap/andhra-pradesh-legislati.jpg"
    },{
        "title": "శ్రీలంకకు పయనమైన భారత జట్టు",
		"content": "ముక్కోణపు టి20 టోర్నీలో పాల్గొనేందుకు రోహిత్‌ శర్మ నేతృత్వంలోని భారత క్రికెట్‌ జట్టు ఆదివారం శ్రీలంక బయల్దేరి వెళ్లింది. మంగళవారం మొదలయ్యే ఈ టోర్నీ తొలి మ్యాచ్‌లో భారత్‌... శ్రీలంకతో తలపడనుంది. మూడు జట్లు ప్రత్యర్థితో రెండేసి మ్యాచ్‌లు ఆడనున్నాయి. ఫైనల్‌ సహా ఈ మ్యాచ్‌లన్నిటికీ కొలంబోలోని ప్రేమదాస స్టేడియమే వేదిక కానుంది.  ",
		"img_url": "https://github.com/VattipalliSridhar/Telugu-Quotes-Wallpapers/raw/master/news/ap/ROHIT-RAINA-LEAVS.jpg"
    },{
        "title": "ఆస్కార్‌’ కేటగిరీ విజేతలు",
		"content": "అమెరికాలోని లాస్‌ఏంజెల్స్‌ డాల్బీ థియేటర్‌లో ఆస్కార్‌ వేడుక అట్టహాసంగా కొనసాగుతోంది.  మిరమిట్లుగొలిపే దుస్తుల్లో తారలు మెరిసిపోతున్నారు. ఇప్పటికే కొన్ని కేటగిరీల్లో విజేతల వివరాలను ప్రకటించారు. 1. సామ్‌ రాక్‌వెల్‌ - ఉత్తమ సహాయనటుడు (త్రీ బిల్‌బోర్డ్స్‌ ఔట్‌సైడ్‌ ఎబ్బింగ్‌)

2. ఫాంటమ్‌ థ్రెడ్‌ - ఉత్తమ వస్త్రాలంకరణ (మార్క్‌ బ్రిడ్జెస్‌)

3. ఐకారస్‌ - బెస్ట్‌ డాక్యుమెంటరీ ఫీచర్‌

4. డార్కెస్ట్‌ అవర్ - ఉత్తమ అలంకరణ, కేశాలంకరణ

5. డంకర్క్‌ - బెస్ట్‌ సౌండ్‌ ఎడిటింగ్‌

6. ద షేప్‌ ఆఫ్‌ వాటర్‌ - బెస్ట్‌ ప్రొడక్షన్‌ డిజైన్‌

7. ఆలిసన్‌ జానీ - ఉత్తమ సహాయనటి

8. కోకో - బెస్ట్‌ యానిమేటెడ్‌ ఫీచర్‌ ఫిల్మ్‌

9. డియర్‌ బాస్కెట్‌ బాల్‌ - బెస్ట్‌ యానిమేటెడ్‌ పార్ట్‌

10. బ్లేడ్‌ రన్నర్‌ 2049- బెస్ట్‌ విజువల్‌ ఎఫెక్ట్స్‌

11. ది సైలెంట్‌ చైల్డ్‌ - బెస్ట్‌ లైవ్‌ యాక్షన్‌ షాట్‌ ",
		"img_url": "https://github.com/VattipalliSridhar/Telugu-Quotes-Wallpapers/raw/master/news/world/asar.JPG"
    }
 
	
	
]
